Metadata-Version: 2.1
Name: mutations
Version: 0.4.0
Summary: Encapsulate your business logic in command classes.
Home-page: http://github.com/omarish/mutations
Author: Omar Bohsali
Author-email: me@omarish.com
License: MIT
Keywords: business logic,django,fat models,thin models,input validation,commands,validation
Platform: UNKNOWN
